{
  "id": 68,
  "title": "can I ever be free from pain, if I am not free from Fear?",
  "slug": "68-can-i-ever-be-free-from-pain-if-i-am-not-free-from-fear",
  "author": "joshualinog",
  "date": "2025-04-29T20:39:32Z",
  "createdAt": "2025-04-29T20:39:32Z",
  "updatedAt": "2026-05-11T16:43:29Z",
  "description": null,
  "template": "basic-body",
  "category": null,
  "mainImage": null,
  "youtube": false,
  "bible": null,
  "links": null,
  "steps": false,
  "tags": [
    "﹖.ᐣ❔🔎 🕵🏻 QUESTION",
    "isPost"
  ],
  "labels": [
    "﹖.ᐣ❔🔎 🕵🏻 QUESTION",
    "isPost"
  ],
  "state": "open",
  "status": "published",
  "excerpt": "if #66 can I ever be free of pain if I'm not free from fear?",
  "body": "if #66 can I ever be free of pain if I'm not free from fear?\n\nif I'm not free from Fear, can I never be free to love?",
  "content": "if #66 can I ever be free of pain if I'm not free from fear?\n\nif I'm not free from Fear, can I never be free to love?",
  "raw_issue": {
    "url": "https://github.com/joshualinog/scribal.bible-CONTENT-CREATION/issues/68",
    "number": 68
  }
}
