{
  "id": 116,
  "title": "💐 S4 GUT ♾️⁷🌈",
  "slug": "116-s4-gut",
  "author": "joshualinog",
  "date": "2025-05-15T12:23:20Z",
  "createdAt": "2025-05-15T12:23:20Z",
  "updatedAt": "2026-05-11T16:42:15Z",
  "description": null,
  "template": "basic-body",
  "category": null,
  "mainImage": null,
  "youtube": false,
  "bible": null,
  "links": null,
  "steps": false,
  "tags": [
    "isPost"
  ],
  "labels": [
    "isPost"
  ],
  "state": "open",
  "status": "published",
  "excerpt": "# 💐 S4 GUT ♾️⁷🌈",
  "body": "# 💐 S4 GUT ♾️⁷🌈",
  "content": "# 💐 S4 GUT ♾️⁷🌈",
  "raw_issue": {
    "url": "https://github.com/joshualinog/scribal.bible-CONTENT-CREATION/issues/116",
    "number": 116
  }
}
