{
  "id": 82,
  "title": "Gospel articulated as we have to get my son back, enlisting enemies to save his son",
  "slug": "gospel-articulated-as-we-have-to-get-my-son-back-enlisting-enemies-to-save-his-son-82",
  "author": {
    "login": null,
    "id": null,
    "url": "https://github.com/joshualinog/scribal.bible-CONTENT-CREATION/issues/82"
  },
  "created_at": "2025-05-06T20:35:34Z",
  "updated_at": "2025-11-07T21:09:50Z",
  "body": "Double entender multiple applications \n- got enlists/sends the word, the mimra, to go from heaven to get his son. He enlists/sends the gentiles to go get his son : his son is Israel \n- God enlists/sends the word, the mimra, to go from heaven to get his son. He enlists/sends Israel to get his son: his son is Adam, the gentiles.\n\nGot attacked and ruined the enmity of Genesis 3 \nWith his gospel god attacked the enmity between the seed of the serpent and the seed of Eve",
  "comments": [
    {
      "author": "joshualinog",
      "body": "God  sent the gentiles to his son, his Son is israel,God sent word to leave Heaven to get his son and he sends Israel to get his son who is Adam who is the gentiles. God attacked and ruined the severe hatred of Genesis 3 with his gospel.\n \n",
      "created_at": "2025-05-07T14:29:37Z"
    }
  ],
  "labels": [
    "isPost"
  ],
  "tags": [],
  "main_category": null,
  "post_type": "article",
  "media": [],
  "assets": [],
  "excerpt": "Double entender multiple applications ",
  "draft": false,
  "custom": {}
}
