{
  "id": 279,
  "title": "Is it ontologically necessary to depict the word as preceding the manifestation of the spirit? Even in the Torah?\n",
  "slug": "is-it-ontologically-necessary-to-depict-the-word-as-preceding-the-manifestation-of-the-spirit-even-in-the-torah-279",
  "author": {
    "login": null,
    "id": null,
    "url": "https://github.com/joshualinog/scribal.bible-CONTENT-CREATION/issues/279"
  },
  "created_at": "2025-10-14T19:57:30Z",
  "updated_at": "2025-11-07T21:14:45Z",
  "body": "# Is it ontologically necessary to depict the word as preceding the manifestation of the spirit? Even in the Torah?\n\n",
  "comments": [],
  "labels": [
    "﹖.ᐣ❔🔎 🕵🏻 QUESTION",
    "𖥂 Trinity",
    "💨🕊️ THE HOLY SPIRIT| Pneumatology",
    "H&E TwofoldYahweh | Cosmological Binitarian Yahweh",
    "Glory Name Face OF YAH / Visible | Earthly YAH",
    "isPost"
  ],
  "tags": [
    "﹖.ᐣ❔🔎 🕵🏻 QUESTION",
    "𖥂 Trinity",
    "💨🕊️ THE HOLY SPIRIT| Pneumatology",
    "H&E TwofoldYahweh | Cosmological Binitarian Yahweh",
    "Glory Name Face OF YAH / Visible | Earthly YAH"
  ],
  "main_category": "﹖.ᐣ❔🔎 🕵🏻 QUESTION",
  "post_type": "article",
  "media": [],
  "assets": [],
  "excerpt": "# Is it ontologically necessary to depict the word as preceding the manifestation of the spirit? Even in the Torah?",
  "draft": false,
  "custom": {}
}
